{"statusCode":200,"body":[{"pointsEarned":5,"zipcode":"03054","date":"2018-10-7 ","actionTaken":"no-straws","updatedAt":1538939537976,"carbonPointsEarned":10000,"createdAt":1538939537976,"username":"divya16","email":"abc@gmail.com","recordedFrequency":2},{"pointsEarned":5,"zipcode":"03054","date":"2018-10-7 ","actionTaken":"no-plastic","updatedAt":1538939556127,"carbonPointsEarned":10000,"createdAt":1538939556127,"username":"divya16","email":"abc@gmail.com","recordedFrequency":2},{"pointsEarned":5,"zipcode":"03054","date":"2018-10-7 ","actionTaken":"save-water","updatedAt":1538939575793,"carbonPointsEarned":10000,"createdAt":1538939575793,"username":"divya16","email":"abc@gmail.com","recordedFrequency":2},{"totalPoints":15},{"totalCarbonPoints":30000}]}